{
  "Еда": {
    "Можно ли со своей едой?": "Конечно!",
    "Какая еда есть в антикафе?": "Печеньки, вафельки и другая закуска к чаю",
    "Можно ли заказать еду в антикафе?": "Естсественно да!"
  },
  "Правила": {
    "Правила антикафе": "Не мешать отдыхать другим людям"
  },
  "Тариф и оплата": {
    "Тариф в антикафе": "2 Рубля минута",
    "Можно ли платить картой?": "Разумеется",
    "Что такое стопчек?": "Cтоп чек это сумма больше которой вы не заплатите даже если проведете у нас весь день"
  },
  "Действующие акции": {
    "Поощрение организаторов": "Организатор похода в коперник посещает нас по тарифу 1р минута",
    "Скидка студентам": "1.5 рублей/минута (90 рублей/час) - 25% скидка для вступивших в нашу группу студентов, аспирантов, преподавателей и выпускников :\n- МАИ до 21 марта 2017 \n- МГУ до 21 марта 2017 \n- РГГУ до 21 марта 2017 \n- МГИМО до 21 марта 2017 \n- РНИМУ им. Н.И.Пирогова до 01 апреля 2017;\n- МГМСУ им. А. И. Евдокимова до 01 апреля 2017;\n- МГППУ до 22 сентября 2017 \n- МГПУ до 22 сентября 2017 \n- РЭУ им. Г. В. Плеханова до 1 октября 2017;\n- НИЯУ МИФИ до 4 октября 2017;\n- ГУУ до 22 октября 2017\n- Первого МГМУ им. И.М. Сеченова! до 1 ноября 2017\n- владельцев карты Ёлка;\n- владельцев карт ISIC, ITIC, IYTC;"},
  "Массовые мероприятия в антикафе": {
    "Вместимость антикафе": "120 посадочных мест",
    "Количество людей и тарифы": "До 120 человек , для массовых мероприятий тарифы обсуждаются отдельно"
  },
  "Общая информация": {
    "Комнаты": "7 комнат +ниши",
    "Чем можно заняться?": "https://vk.com/topic-38855551_31783614",
    "Техника и настолки": "10 приставок 100 настолок",
    "Режим работы": "с 11 до 23.00",
    "Расположение": "Москва, Мытная 52",
    "Парковка": "Бесплатная стихийная",
    "Как пройти от метро": "https://vk.com/topic-38855551_30312915"
  },
  "Контакты": {
    "Телефон": "+79037900929",
    "Социальные сети": "https://vk.com/pvk_kopernik"
  }

}
